vulavula-0.4.3.dist-info/METADATA
vulavula-0.4.3.dist-info/WHEEL
vulavula-0.4.3.dist-info/entry_points.txt
vulavula/__init__.py
vulavula/client/__init__.py
vulavula/client/client.py
vulavula/client/nlu.py
vulavula/client/sentiment.py
vulavula/client/transcribe.py
vulavula/client/translation.py
vulavula/client/transport.py
vulavula/client/vulavula_search.py
vulavula/common/__init__.py
vulavula/common/error_handler.py
vulavula/common/response_handler.py
vulavula/config/__init__.py
vulavula/config/config.py
vulavula/models/__init__.py
vulavula/models/types/__init__.py
vulavula/models/types/entity_recognition.py
vulavula/models/types/intent_classification.py
vulavula/models/types/sentiment_analysis.py
vulavula/models/types/translation.py
vulavula/models/types/vulavula_search.py
vulavula-0.4.3.dist-info/RECORD
