Metadata-Version: 2.1
Name: vulavula
Version: 0.4.3
Summary: The vulavula Python SDK provides access to the Vulavula API.
Keywords: lelapa,vulavula,nlp,intent,multilingual,transcription
Author-Email: Raphael Karanja <raphael.karanja@lelapa.ai>
License: MIT
Classifier: Intended Audience :: Developers
Classifier: Programming Language :: Python
Classifier: Programming Language :: Python :: 3
Project-URL: Homepage, https://github.com/Lelapa-AI/vulavula-sdk
Requires-Python: >=3.8
Requires-Dist: requests>=2.31.0
Requires-Dist: pydantic[dotenv]<2,>=1.10.16
Requires-Dist: PyPDF2>=3.0.1
